lds_python/__init__.py
lds_python/inference.py
lds_python/learning.py
lds_python/simulation.py
lds_python-1.0.0.dist-info/METADATA
lds_python-1.0.0.dist-info/WHEEL
lds_python-1.0.0.dist-info/top_level.txt
lds_python-1.0.0.dist-info/RECORD
