Metadata-Version: 2.1
Name: lds-python
Version: 1.0.0
Summary: Linear Dynamical Systems
Home-page: https://github.com/joacorapela/lds_python
Author: Joaquin Rapela
Author-email: j.rapela@ucl.ac.uk
License: MIT
Classifier: License :: OSI Approved :: MIT License
Classifier: Programming Language :: Python :: 3.9
Requires-Python: >=3.9
Requires-Dist: numpy
Requires-Dist: scipy
Requires-Dist: torch
Provides-Extra: docs
Requires-Dist: sphinx-gallery ; extra == 'docs'
Requires-Dist: sphinxcontrib-bibtex ; extra == 'docs'
Requires-Dist: plotly ; extra == 'docs'
Requires-Dist: kaleido ; extra == 'docs'
